pydd/__init__.py
pydd/__main__.py
pydd/cli/__init__.py
pydd/dbg/__init__.py
pydd/dbg/tickrate.py
pydd/lib/__init__.py
pydd-0.2016.8.2.dist-info/DESCRIPTION.rst
pydd-0.2016.8.2.dist-info/METADATA
pydd-0.2016.8.2.dist-info/RECORD
pydd-0.2016.8.2.dist-info/WHEEL
pydd-0.2016.8.2.dist-info/entry_points.txt
pydd-0.2016.8.2.dist-info/metadata.json
pydd-0.2016.8.2.dist-info/top_level.txt
