Metadata-Version: 2.0
Name: pydd
Version: 0.2016.8.2
Summary: asorted tools for development and debugging
Home-page: https://poncki.pl/
Author: poncki
Author-email: pydd@poncki.pl
License: don't know not yet, MIT probably
Platform: UNKNOWN
Requires-Dist: click
Requires-Dist: colorama
